pure_framework/__init__.py
pure_framework/application.py
pure_framework/async_application.py
pure_framework/async_decorators.py
pure_framework/async_middleware.py
pure_framework/decorators.py
pure_framework/dependency_injection.py
pure_framework/errors.py
pure_framework/framework_types.py
pure_framework/http.py
pure_framework/middleware.py
pure_framework/routing.py
pure_framework/swagger.py
pure_framework/test_client.py
pure_framework/validation.py
pure_framework-0.0.4.dist-info/licenses/LICENSE
pure_framework-0.0.4.dist-info/METADATA
pure_framework-0.0.4.dist-info/WHEEL
pure_framework-0.0.4.dist-info/entry_points.txt
pure_framework-0.0.4.dist-info/top_level.txt
pure_framework-0.0.4.dist-info/RECORD
