Metadata-Version: 2.4
Name: pure-framework
Version: 0.0.4
Summary: A modern, lightweight Python web framework with type safety, dependency injection, middleware pipelines, async support, request validation, enhanced error handling, and auto-generated API documentation.
Author-email: Hasan Ragab <hr145310@gmail.com>
Maintainer-email: Hasan Ragab <hr145310@gmail.com>
License: MIT
Project-URL: Homepage, https://github.com/HasanRagab/pure_framework
Project-URL: Documentation, https://github.com/HasanRagab/pure_framework#readme
Project-URL: Repository, https://github.com/HasanRagab/pure_framework.git
Project-URL: Issues, https://github.com/HasanRagab/pure_framework/issues
Project-URL: Changelog, https://github.com/HasanRagab/pure_framework/blob/main/CHANGELOG.md
Keywords: web-framework,rest-api,microservice,http-server,dependency-injection,middleware,type-safety,swagger,openapi,pure-python,lightweight,modern,async,asyncio,validation,error-handling,testing,cli-tool
Classifier: Development Status :: 4 - Beta
Classifier: Environment :: Web Environment
Classifier: Framework :: AsyncIO
Classifier: Intended Audience :: Developers
Classifier: License :: OSI Approved :: MIT License
Classifier: Natural Language :: English
Classifier: Operating System :: OS Independent
Classifier: Programming Language :: Python :: 3
Classifier: Programming Language :: Python :: 3.9
Classifier: Programming Language :: Python :: 3.10
Classifier: Programming Language :: Python :: 3.11
Classifier: Programming Language :: Python :: 3.12
Classifier: Programming Language :: Python :: 3.13
Classifier: Programming Language :: Python :: 3 :: Only
Classifier: Topic :: Internet :: WWW/HTTP :: HTTP Servers
Classifier: Topic :: Internet :: WWW/HTTP :: WSGI :: Application
Classifier: Topic :: Software Development :: Libraries :: Application Frameworks
Classifier: Topic :: Software Development :: Libraries :: Python Modules
Classifier: Topic :: System :: Networking
Classifier: Typing :: Typed
Requires-Python: >=3.9
License-File: LICENSE
Provides-Extra: dev
Requires-Dist: pytest>=7.0.0; extra == "dev"
Requires-Dist: pytest-cov>=4.0.0; extra == "dev"
Requires-Dist: black>=22.0.0; extra == "dev"
Requires-Dist: isort>=5.10.0; extra == "dev"
Requires-Dist: flake8>=5.0.0; extra == "dev"
Requires-Dist: mypy>=1.0.0; extra == "dev"
Requires-Dist: pre-commit>=2.20.0; extra == "dev"
Requires-Dist: twine>=4.0.0; extra == "dev"
Requires-Dist: build>=0.8.0; extra == "dev"
Provides-Extra: docs
Requires-Dist: mkdocs>=1.4.0; extra == "docs"
Requires-Dist: mkdocs-material>=8.5.0; extra == "docs"
Requires-Dist: mkdocstrings[python]>=0.19.0; extra == "docs"
Provides-Extra: test
Requires-Dist: pytest>=7.0.0; extra == "test"
Requires-Dist: pytest-cov>=4.0.0; extra == "test"
Requires-Dist: pytest-asyncio>=0.21.0; extra == "test"
Requires-Dist: httpx>=0.24.0; extra == "test"
Dynamic: license-file
